<?xml version="1.0"?>
<metadata>
	<idinfo>
		<citation>
			<citeinfo>
				<origin>Metro Data Resource Center</origin>
				<pubdate>1988</pubdate>
				<title>Major Rivers (poly)</title>
			</citeinfo>
		</citation>
		<descript>
			<abstract>Major rivers and water bodies derived from Metro's Riv_poly data layer. Includes: the Columbia, Willamette, Sandy, Clackamas and Lewis Rivers; Lake Oswego; Smith, Bybee, Vancouver and Sturgeon Lakes.</abstract>
			<purpose>For general mapping purposes.</purpose>
			<supplinf></supplinf>
		</descript>
		<timeperd>
			<timeinfo>
				<sngdate>
					<caldate>20080130</caldate>
				</sngdate>
			</timeinfo>
			<current>Ground condition</current>
		</timeperd>
		<status>
			<progress>Complete</progress>
			<update>As needed</update>
		</status>
		<spdom>
			<bounding>
				<westbc>-123.785577699</westbc>
				<eastbc>-121.440498206</eastbc>
				<northbc>46.3880499964</northbc>
				<southbc>44.6838701483</southbc>
			</bounding>
		</spdom>
		<keywords>
			<theme>
				<themekt>None</themekt>
				<themekey>River</themekey>
				<themekey>stream</themekey>
				<themekey>creek</themekey>
				<themekey>lake</themekey>
				<themekey>slough</themekey>
				<themekey>drainage</themekey>
				<themekey>hydrography</themekey>
				<themekey>hydrology</themekey>
			</theme>
			<place>
				<placekt>None</placekt>
				<placekey>Portland</placekey>
				<placekey>Multnomah County</placekey>
				<placekey>Washington County</placekey>
				<placekey>Clackamas County</placekey>
				<placekey>Oregon</placekey>
				<placekey>Clark County</placekey>
				<placekey>Washington</placekey>
			</place>
		</keywords>
		<accconst>None</accconst>
		<useconst>This database and GIS data are made available under the Open Database License (ODbL v1) and Database Content License (DbCL v1). See http://www.oregongmetro.gov/rlis-live.</useconst>
		<browse>
			<browsen>http://library.oregonmetro.gov/rlisdiscovery/browse_graphic/mjriv_fi.png</browsen>
			<browsed>Rivers and streams shown with topography.</browsed>
			<browset>PNG</browset>
		</browse>
	</idinfo>
	<dataqual>
		<logic></logic>
		<complete></complete>
		<posacc>
			<horizpa>
				<horizpar>Same as Metro's Riv_poly data layer. The Riv_poly layer was intially registered to the US Geological Survey (USGS) 7.5 minute quadrangles, and then adjusted visually at approximately 1:10000 using the 1998 Spencer Gross aerial photography.  Where photography was not available or banks and streambeds obscured, the USGS quad topography was used. Some of the major streams are registered to the tax lot map.</horizpar>
			</horizpa>
		</posacc>
		<lineage>
			<procstep>
				<procdesc>Derived from Metros Riv_poly data layer which is an updated river and water body data layer of the Metro region created by using the previous Metro river and water body layer (an enhanced USGS hydrography layer which had been adjusted to taxlots). River and water body banks were adjusted or digitized at approximately 1:10000 using the 1998 Spencer Gross aerial photography. Where photography was not available or banks and riverbeds obscured, the USGS quad topography was used. The dataset has not been field checked.</procdesc>
				<procdate>200102</procdate>
			</procstep>
			<procstep>
				<procdesc>Projection information (.prj file), compatible with ArcGIS 8.1, was added to the layer.</procdesc>
				<procdate>20010715</procdate>
			</procstep>
			<procstep>
				<procdesc>Incorporated Clean Water Services line work in much of the Tualatin River subbasin.</procdesc>
				<procdate>200607</procdate>
			</procstep>
			<procstep>
				<procdesc>Changed native SDE storage precision from low to high</procdesc>
				<procdate>20100122</procdate>
			</procstep>
		</lineage>
	</dataqual>
	<spdoinfo>
		<direct>Vector</direct>
		<ptvctinf>
			<sdtsterm>
				<sdtstype>Polygon</sdtstype>
			</sdtsterm>
		</ptvctinf>
	</spdoinfo>
	<spref>
		<horizsys>
			<planar>
				<gridsys>
					<gridsysn>NAD_1983_HARN_StatePlane_Oregon_North_FIPS_3601</gridsysn>
					<spcs>
						<spcszone>5076</spcszone>
					</spcs>
				</gridsys>
				<planci>
					<plance></plance>
					<plandu>International foot</plandu>
				</planci>
			</planar>
			<geodetic>
				<horizdn>D_North_American_1983_HARN</horizdn>
				<ellips></ellips>
				<semiaxis></semiaxis>
				<denflat></denflat>
			</geodetic>
		</horizsys>
	</spref>
	<eainfo>
		<detailed>
			<enttyp>
				<enttypl>Mjriv_fi.dbf</enttypl>
				<enttypd>Major river polygon attributes</enttypd>
				<enttypds></enttypds>
			</enttyp>
			<attr>
				<attrlabl>Class</attrlabl>
				<attrdef>Class of water body</attrdef>
				<attrdefs></attrdefs>
				<attrdomv>
					<edom>
						<edomv>1</edomv>
						<edomvd>Major water body</edomvd>
						<edomvds></edomvds>
					</edom>
					<edom>
						<edomv>2</edomv>
						<edomvd>Important water body</edomvd>
						<edomvds></edomvds>
					</edom>
					<udom>NA</udom>
				</attrdomv>
			</attr>
			<attr>
				<attrlabl>Area</attrlabl>
				<attrdef>Area in square feet</attrdef>
				<attrdefs></attrdefs>
				<attrdomv>
					<udom>NA</udom>
				</attrdomv>
			</attr>
		</detailed>
	</eainfo>
	<distinfo>
		<distrib>
			<cntinfo>
				<cntorgp>
					<cntorg>Metro Data Resource Center</cntorg>
				</cntorgp>
				<cntaddr>
					<addrtype></addrtype>
					<address>600 NE Grand Ave.</address>
					<city>Portland</city>
					<state>OR</state>
					<postal>97232</postal>
				</cntaddr>
				<cntvoice>503 797-1742</cntvoice>
				<cntfax>503 797-1909</cntfax>
				<cntemail>drc@oregonmetro.gov</cntemail>
			</cntinfo>
		</distrib>
		<distliab>The information in this file was derived from digital databases on Metro's GIS. Care was taken in the creation of this file. Metro cannot accept any responsibility for errors, omissions, or positional accuracy. There are no warranties, expressed or implied.</distliab>
		<stdorder>
			<digform>
				<digtinfo>
					<formname>Shapefile</formname>
					<transize>1 mb</transize>
				</digtinfo>
				<digtopt>
					<offoptn>
						<offmedia>DVD or CD-ROM</offmedia>
						<recfmt>ISO9660</recfmt>
					</offoptn>
					<onlinopt>
						<computer>
							<networka>
								<networkr>http://www.oregonmetro.gov/rlisdiscovery</networkr>
							</networka>
						</computer>
						<accinstr>Email drc@oregonmetro.gov or call 503-797-1742 for further instructions.</accinstr>
					</onlinopt>
				</digtopt>
			</digform>
			<fees>No cost</fees>
		</stdorder>
	</distinfo>
	<metainfo>
		<metd>20100126</metd>
		<metc>
			<cntinfo>
				<cntorgp>
					<cntorg>Metro Data Resource Center</cntorg>
					<cntper>Minott Kerr</cntper>
				</cntorgp>
				<cntaddr>
					<addrtype>mailing and physical address</addrtype>
					<address>600 NE Grand Ave.</address>
					<city>Portland</city>
					<state>OR</state>
					<postal>97232</postal>
				</cntaddr>
				<cntvoice>503 797-1679</cntvoice>
				<cntfax>503 797-1909</cntfax>
				<cntemail>minott.kerr@oregonmetro.gov</cntemail>
			</cntinfo>
		</metc>
		<metstdn>FGDC Content Standards for Digital Geospatial Metadata</metstdn>
		<metstdv>FGDC-STD-001-1998</metstdv>
	</metainfo>
	<Esri><DataProperties><itemProps><itemLocation><linkage Sync="TRUE">file://\\GIS-WORKSTATION\Users\arcgisone\Downloads\Portland_template\mjriv_fi</linkage><protocol Sync="TRUE">Local Area Network</protocol></itemLocation></itemProps><copyHistory><copy source="C:\Users\arcgisone\Downloads\Portland_template\Portland_template\mjriv_fi" dest="\\GIS-WORKSTATION\Users\arcgisone\Downloads\Portland_template\mjriv_fi" date="20141105" time="15395200"></copy></copyHistory></DataProperties><CreaDate>20150308</CreaDate><CreaTime>14252200</CreaTime><ArcGISFormat>1.0</ArcGISFormat><SyncOnce>TRUE</SyncOnce></Esri></metadata>
